BUGS.txt
CHANGES.txt
COPYING
INSTALL.txt
LICENSE.txt
MANIFEST.in
README.txt
TODO.txt
ez_setup.py
setup.py
src/tome/Tome.py
src/tome/__init__.py
src/tome/main.py
src/tome/tomeTempl.py
src/tome/version.py
src/tome/wrapUtil.py
src/tome/writeEpub.py
src/tome/writeFlow.py
src/tome/writeLatex.py
src/tome/writeText.py
src/tome.egg-info/PKG-INFO
src/tome.egg-info/SOURCES.txt
src/tome.egg-info/dependency_links.txt
src/tome.egg-info/entry_points.txt
src/tome.egg-info/requires.txt
src/tome.egg-info/top_level.txt
src/tome/doc/EPUB_HTML.otl
src/tome/doc/EPUB_TEMPL.otl
src/tome/doc/tome-flow.otl
src/tome/res/template.latex.tmpl
src/tome/res/tome-devel.jpeg
src/tome/res/tome.jpeg
src/tome/res/epub-template/bookTitle.xhtml.tmpl
src/tome/res/epub-template/chapter.xhtml.tmpl
src/tome/res/epub-template/content.opf.tmpl
src/tome/res/epub-template/endnotes.xhtml.tmpl
src/tome/res/epub-template/frontcover.xhtml.tmpl
src/tome/res/epub-template/nav.xhtml.tmpl
src/tome/res/epub-template/page-template.xpgt
src/tome/res/epub-template/partTitle.xhtml.tmpl
src/tome/res/epub-template/stylesheet.css
src/tome/res/epub-template/title_page.xhtml.tmpl
src/tome/res/epub-template/toc.ncx.tmpl
src/tome/res/epub-template/toc.xhtml.tmpl
src/tome/res/epub-template/META-INF/container.xml