Metadata-Version: 1.0
Name: tome
Version: 1.5.0.0-r12
Summary: Tome Markup Language for authors.
Home-page: https://bitbucket.org/bmearns/tome/
Author: Brian Mearns
Author-email: bmearns@ieee.org
License:                     GNU AFFERO GENERAL PUBLIC LICENSE
